README.txt
setup.py
Products/__init__.py
Products.LinguaFace.egg-info/PKG-INFO
Products.LinguaFace.egg-info/SOURCES.txt
Products.LinguaFace.egg-info/dependency_links.txt
Products.LinguaFace.egg-info/entry_points.txt
Products.LinguaFace.egg-info/namespace_packages.txt
Products.LinguaFace.egg-info/not-zip-safe
Products.LinguaFace.egg-info/requires.txt
Products.LinguaFace.egg-info/top_level.txt
Products/LinguaFace/ABOUT
Products/LinguaFace/CHANGES
Products/LinguaFace/LICENSE
Products/LinguaFace/LinguaFaceTool.py
Products/LinguaFace/README.txt
Products/LinguaFace/__init__.py
Products/LinguaFace/analytics_icon.gif
Products/LinguaFace/config.py
Products/LinguaFace/configure.zcml
Products/LinguaFace/linguaface_icon.gif
Products/LinguaFace/overrides.zcml
Products/LinguaFace/patches.py
Products/LinguaFace/setuphandlers.py
Products/LinguaFace/version.txt
Products/LinguaFace/browser/__init__.py
Products/LinguaFace/browser/foldercontents.pt
Products/LinguaFace/browser/foldercontents.py
Products/LinguaFace/browser/interfaces.py
Products/LinguaFace/browser/navigation.py
Products/LinguaFace/browser/navtree.py
Products/LinguaFace/browser/utilities.py
Products/LinguaFace/doc/FAQ
Products/LinguaFace/doc/SCREENSHOTS
Products/LinguaFace/doc/icon.png
Products/LinguaFace/doc/translation.png
Products/LinguaFace/events/__init__.py
Products/LinguaFace/events/handlers.py
Products/LinguaFace/exportimport/__init__.py
Products/LinguaFace/exportimport/configure.zcml
Products/LinguaFace/exportimport/tool.py
Products/LinguaFace/interface/__init__.py
Products/LinguaFace/interface/tool.py
Products/LinguaFace/interface/translatable.py
Products/LinguaFace/profiles/default/catalog.xml
Products/LinguaFace/profiles/default/cssregistry.xml
Products/LinguaFace/profiles/default/export_steps.xml
Products/LinguaFace/profiles/default/import_steps.xml
Products/LinguaFace/profiles/default/jsregistry.xml
Products/LinguaFace/profiles/default/skins.xml
Products/LinguaFace/profiles/default/toolset.xml
Products/LinguaFace/skins/linguaface/content_status_modify.cpy
Products/LinguaFace/skins/linguaface/content_status_modify.cpy.metadata
Products/LinguaFace/skins/linguaface/createTranslation_back.cpy
Products/LinguaFace/skins/linguaface/createTranslation_back.cpy.metadata
Products/LinguaFace/skins/linguaface/deleteTranslations.cpy
