Metadata-Version: 1.0
Name: Products.LinguaFace
Version: 3.0.0
Summary: A product provinding an alternate view and behaviour for LinguaPlone
Home-page: http://pypi.python.org/pypi/Products.LinguaFace
Author: Alter Way Solutions
Author-email: support@alterway.fr
License: GPL
Keywords: plone linguaplone
Platform: UNKNOWN
Classifier: Programming Language :: Python
Classifier: Framework :: Plone
